tpng/__init__.py
tpng/__main__.py
tpng/tpng.py
tpng.py-0.2.5.dist-info/LICENSE
tpng.py-0.2.5.dist-info/METADATA
tpng.py-0.2.5.dist-info/WHEEL
tpng.py-0.2.5.dist-info/top_level.txt
tpng.py-0.2.5.dist-info/RECORD
