Metadata-Version: 2.1
Name: tpng.py
Version: 0.2.5
Summary: A special file format for displaying images in the terminal.
Home-page: https://github.com/romanin-rf/tpng.py
Author: programmer-from-parlament
Author-email: semina054@gmail.com
License: MIT
Keywords: tpng.py
Platform: UNKNOWN
Requires: pillow
Requires: rich
License-File: LICENSE
